memory.v
module memory #(
    parameter DATA_WIDTH = 32,
    parameter ADDR_WIDTH = 32,
    parameter BLOCK_SIZE = 16
)(
    input wire clk,
    input wire rst_n,
    
    // L2 Cache interface
    input wire [ADDR_WIDTH-1:0] addr,
    input wire [BLOCK_SIZE-1:0][DATA_WIDTH-1:0] data_in,
    output reg [BLOCK_SIZE-1:0][DATA_WIDTH-1:0] data_out,
    input wire read,
    input wire write,
    output reg hit,
    output reg ready
);
    localparam BLOCK_BITS = $clog2(BLOCK_SIZE);
    localparam MEM_SIZE = (1 << ADDR_WIDTH);

    reg [DATA_WIDTH-1:0] mem [0:MEM_SIZE - 1]; // Memory array

    wire [ADDR_WIDTH - 1:0] block_start;

    assign block_start = {addr[ADDR_WIDTH - 1:BLOCK_BITS], {BLOCK_BITS{1'b0}}}; // Align address to block size
    
    // Mem read operation
    always @(posedge clk) begin
        if (!rst_n) begin
            ready <= 1'b0;
            hit <= 1'b0;
            data_out <= 0;
            for (integer i = 0; i < MEM_SIZE; i = i + 1) begin
                mem[i] <= i;
            end
        end else if (read) begin
            // $display("Read from memory: %h", addr);
            for (integer i = 0; i < BLOCK_SIZE; i = i + 1) begin
                data_out[i] <= mem[block_start + i];
            end
            $display("%0t [MEM] Mem hit: addr = %h, data = %h", $time, addr, mem[block_start]);
            ready <= 1'b1;
            hit <= 1'b1;
        end else begin
            ready <= 1'b0;
            hit   <= 1'b0;
        end
    end
endmodule

l1_cache.v
module L1_cache #(
    parameter DATA_WIDTH = 32,
    parameter ADDR_WIDTH = 32,
    parameter CACHE_SIZE = 1024,
    parameter BLOCK_SIZE = 16,
    parameter NUM_WAYS = 4
)(
    input wire clk,
    input wire rst_n,
    
    // CPU interface
    input wire [ADDR_WIDTH-1:0] cpu_addr,
    input wire [DATA_WIDTH-1:0] cpu_data_in,
    output reg [DATA_WIDTH-1:0] cpu_data_out,
    input wire cpu_read,
    input wire cpu_write,
    output reg cpu_ready,
    output l1_hit,
    
    // L2 Cache interface
    output reg [ADDR_WIDTH-1:0] l2_cache_addr,
    output reg [BLOCK_SIZE-1:0][DATA_WIDTH-1:0] l2_cache_data_out, // Data to be written to l2 cache
    input wire [BLOCK_SIZE-1:0][DATA_WIDTH-1:0] l2_cache_data_in, // Data read from l2 cache
    output reg l2_cache_read,
    output reg l2_cache_write,
    input wire l2_cache_ready,
    input wire l2_cache_hit
);
    localparam NUM_BLOCKS = CACHE_SIZE / BLOCK_SIZE;
    localparam NUM_SETS = NUM_BLOCKS / NUM_WAYS;
    localparam INDEX_WIDTH = $clog2(NUM_SETS);
    localparam BYTE_OFFSET_WIDTH = $clog2(BLOCK_SIZE);
    localparam TAG_WIDTH = ADDR_WIDTH - INDEX_WIDTH - BYTE_OFFSET_WIDTH;

    // cache line structure
    reg [TAG_WIDTH-1:0] tags[NUM_SETS-1:0][NUM_WAYS-1:0];
    reg [BLOCK_SIZE-1:0][DATA_WIDTH-1:0] data[NUM_SETS-1:0][NUM_WAYS-1:0];
    reg valid[NUM_SETS-1:0][NUM_WAYS-1:0];

    // decompose address into tag, index, and byte offset
    wire [INDEX_WIDTH-1:0] index;
    wire [BYTE_OFFSET_WIDTH-1:0] byte_offset;
    wire [TAG_WIDTH-1:0] tag;

    // assign index, byte_offset, and tag
    assign index = cpu_addr[INDEX_WIDTH+BYTE_OFFSET_WIDTH-1:BYTE_OFFSET_WIDTH];
    assign byte_offset = cpu_addr[BYTE_OFFSET_WIDTH-1:0];
    assign tag = cpu_addr[ADDR_WIDTH-1:INDEX_WIDTH+BYTE_OFFSET_WIDTH];

    // cache hit detection
    reg hit;
    reg updated;
    integer i;
    reg found;
    reg [DATA_WIDTH-1:0] data_found;
    reg reading_from_l2;

    assign l1_hit = hit;

    // set found and data_found
    always @(*) begin
        found = 1'b0;
        data_found = {DATA_WIDTH{1'b0}};
        for (i = 0; i < NUM_WAYS; i = i + 1) begin
            if (valid[index][i] && (tags[index][i] == tag)) begin
                found = 1'b1;
                data_found = data[index][i][byte_offset];
            end
        end
    end

    // set updated signal
    always @(*) begin
        updated = 1'b0;
        for (i = 0; i < NUM_WAYS; i = i + 1) begin
            if (!valid[index][i]) begin
                updated = 1'b1;
            end
        end
    end

    always @(posedge clk) begin
        if (!rst_n) begin
            cpu_ready <= 1'b1;
            l2_cache_read <= 1'b0;
            l2_cache_write <= 1'b0;
            l2_cache_addr <= 0;
            l2_cache_data_out <= 0;
            for (i = 0; i < NUM_SETS; i = i + 1) begin
                for (integer j = 0; j < NUM_WAYS; j = j + 1) begin
                    valid[i][j] <= 1'b0;
                end
            end 
            reading_from_l2 <= 1'b0;
        end else if (reading_from_l2) begin
            if (l2_cache_ready) begin
                l2_cache_read <= 1'b0;
                l2_cache_write <= 1'b0;
                l2_cache_addr <= {ADDR_WIDTH{1'b0}};
                l2_cache_data_out <= l2_cache_data_in;
                reading_from_l2 <= 1'b0;

                // Write data to L1 cache
                for (i = 0; i < NUM_WAYS; i = i + 1) begin
                    if (!valid[index][i]) begin
                        tags[index][i] <= tag;
                        data[index][i] <= l2_cache_data_in;
                        valid[index][i] <= 1'b1;
                    end
                end

                if (!updated) begin
                    tags[index][0] <= tag;
                    data[index][0] <= l2_cache_data_in;
                    valid[index][0] <= 1'b1;
                end
                cpu_ready <= 1'b1;
                cpu_data_out <= l2_cache_data_in[byte_offset];
                hit <= 1'b1;
            end
        end else if (cpu_read) begin
            if (found) begin
                cpu_ready <= 1'b1;
                hit <= 1'b1;
                cpu_data_out <= data_found;
                l2_cache_read <= 1'b0;
                l2_cache_write <= 1'b0;
            end else begin
                cpu_ready <= 1'b0;
                hit <= 1'b0;
                l2_cache_read <= 1'b1;
                l2_cache_write <= 1'b0;
                l2_cache_addr <= cpu_addr;
                reading_from_l2 <= 1'b1;
            end
        end else begin
            $display("CPU write request: addr = %h, data = %h", cpu_addr, cpu_data_in);
        end
    end

    

    
endmodule

tb_l1_cache.v
`timescale 1ns/1ns

module tb_l1_cache;
  //--------------------------------------------------------------------------
  // Parameters
  //--------------------------------------------------------------------------
  parameter ADDR_WIDTH  = 11;
  parameter DATA_WIDTH  = 8;
  parameter CACHE_SIZE  = 256;
  parameter BLOCK_SIZE  = 16;
  parameter NUM_WAYS    = 4;

  //--------------------------------------------------------------------------
  // Clock, reset, and DUT I/O
  //--------------------------------------------------------------------------
  reg                         clk;
  reg                         rst_n;

  // CPU side
  reg  [ADDR_WIDTH-1:0]       cpu_addr;
  reg  [DATA_WIDTH-1:0]       cpu_data_in;
  reg                         cpu_read;
  reg                         cpu_write;
  wire [DATA_WIDTH-1:0]       cpu_data_out;
  wire                        cpu_ready;

  // L2 data as packed array to match DUT ports
  integer w;
  wire  [BLOCK_SIZE-1:0][DATA_WIDTH-1:0] l2_cache_data_in;
  wire [BLOCK_SIZE-1:0][DATA_WIDTH-1:0] l2_cache_data_out;
  wire                        l2_cache_ready;
  wire                        l2_cache_hit;

  // L2 side (stimulus)
  wire [ADDR_WIDTH-1:0]       l2_cache_addr;
  wire                        l2_cache_read;
  wire                        l2_cache_write;

  //--------------------------------------------------------------------------
  // Instantiate L1 cache
  //--------------------------------------------------------------------------
  L1_cache #(
    .ADDR_WIDTH (ADDR_WIDTH),
    .DATA_WIDTH (DATA_WIDTH),
    .CACHE_SIZE (CACHE_SIZE),
    .BLOCK_SIZE (BLOCK_SIZE),
    .NUM_WAYS   (NUM_WAYS)
  ) dut (
    .clk              (clk),
    .rst_n            (rst_n),
    .cpu_addr         (cpu_addr),
    .cpu_data_in      (cpu_data_in),
    .cpu_read         (cpu_read),
    .cpu_write        (cpu_write),
    .cpu_data_out     (cpu_data_out),
    .cpu_ready        (cpu_ready),
    .l1_hit           (),
    .l2_cache_addr    (l2_cache_addr),
    .l2_cache_data_out(l2_cache_data_out),
    .l2_cache_data_in (l2_cache_data_in),
    .l2_cache_read    (l2_cache_read),
    .l2_cache_write   (l2_cache_write),
    .l2_cache_ready   (l2_cache_ready),
    .l2_cache_hit     (l2_cache_hit)
  );

  // Instantiate memory model
  memory #(
    .ADDR_WIDTH (ADDR_WIDTH),
    .DATA_WIDTH (DATA_WIDTH),
    .BLOCK_SIZE (BLOCK_SIZE)
  ) mem_inst (
    .clk    (clk),
    .rst_n  (rst_n),
    .read   (l2_cache_read),
    .write  (l2_cache_write),
    .addr   (l2_cache_addr),
    .data_in(l2_cache_data_out),
    .data_out(l2_cache_data_in),
    .hit    (l2_cache_hit),
    .ready  (l2_cache_ready)
  );

  //--------------------------------------------------------------------------
  // Clock generator: 100 MHz
  //--------------------------------------------------------------------------
  initial clk = 0;
  always #5 clk = ~clk;

  //--------------------------------------------------------------------------
  // Reset pulse
  //--------------------------------------------------------------------------
  initial begin
    rst_n = 0;
    #20;
    rst_n = 1;
  end

  //--------------------------------------------------------------------------
  // Simple task to issue a read from the CPU
  //--------------------------------------------------------------------------
  task cpu_request(input [ADDR_WIDTH-1:0] addr);
  begin
    cpu_addr = addr;
    cpu_read = 1;
    @(posedge clk);
  end
  endtask

  //--------------------------------------------------------------------------
  // Test sequence
  //--------------------------------------------------------------------------
  initial begin
    // Initialize stimulus
    cpu_addr         = 0;
    cpu_read         = 0;
    cpu_write        = 0;
    cpu_data_in      = 0;

    // Wait until reset is released
    @(posedge rst_n);
    $display("%0t [TEST] Reset released", $time);


    // -----------------------------------------------------------------
    // Test for index 0
    // -----------------------------------------------------------------


    // 1) COMPULSORY MISS @ addr = 0
    cpu_request(11'h001);
    // Wait for the cache to assert a request to L2
    wait (l2_cache_read == 1);
    $display("Reading from L2 cache");
    // Wait for memory to respond
    wait (l2_cache_ready == 1);
    // Wait for the cache to finish
    wait (cpu_ready == 1);
    $display("%0t [TEST] Miss @001 -> data_out = %h (expected 001)", $time, cpu_data_out);

    // 2) HIT on the nearby address
    cpu_request(11'h000);
    // @(posedge clk);
    // @(posedge clk);
    if (cpu_ready && cpu_data_out == 8'h00)
      $display("%0t [TEST] Hit after allocate @000 PASS", $time);
    else
      $display("%0t [TEST] Hit after allocate @000 FAIL: ready=%b, data_out=%h",
                $time, cpu_ready, cpu_data_out);
    
    // 3) HIT on the nearby address
    cpu_request(11'h002);
    if (cpu_ready && cpu_data_out == 8'h02)
      $display("%0t [TEST] Hit after allocate @002 PASS", $time);
    else
      $display("%0t [TEST] Hit after allocate @002 FAIL: ready=%b, data_out=%h",
                $time, cpu_ready, cpu_data_out);
    // 4) HIT on the nearby address
    cpu_request(11'h005);
    if (cpu_ready && cpu_data_out == 8'h05)
      $display("%0t [TEST] Hit after allocate @005 PASS", $time);
    else
      $display("%0t [TEST] Hit after allocate @005 FAIL: ready=%b, data_out=%h",
                $time, cpu_ready, cpu_data_out);


    // -----------------------------------------------------------------
    // Test for index 1
    // -----------------------------------------------------------------


    // 1) COMPULSORY MISS @ addr = 0x010 (index=1 if BLOCK_SIZE=16)
    cpu_request(11'h010);
    wait (l2_cache_read == 1);
    // Wait for memory to respond
    wait (l2_cache_ready == 1);
    wait (cpu_ready == 1);
    $display("%0t [TEST] Miss @0x010 -> data_out = %h (expected 010)", $time, cpu_data_out);

    // 2) HIT 
    cpu_request(11'h014);
    if (cpu_ready && cpu_data_out == 8'h14)
      $display("%0t [TEST] Hit after allocate @0x014 PASS", $time);
    else
      $display("%0t [TEST] Hit after allocate @0x014 FAIL: ready=%b, data_out=%h",
                $time, cpu_ready, cpu_data_out);
              
    // 3) HIT
    cpu_request(11'h01A);
    // @(posedge clk);
    // @(posedge clk);
    if (cpu_ready && cpu_data_out == 8'h1A)
      $display("%0t [TEST] Hit after allocate @0x01A PASS", $time);
    else
      $display("%0t [TEST] Hit after allocate @0x01A FAIL: ready=%b, data_out=%h",
                $time, cpu_ready, cpu_data_out);


    // ----------------------------------------------------------------
    // Test for eviction of index 0
    // ----------------------------------------------------------------
    cpu_request(11'h101);
    wait (l2_cache_read == 1);
    // Wait for memory to respond
    wait (l2_cache_ready == 1);
    wait (cpu_ready == 1);
    $display("%0t [TEST] Miss @0x101 -> data_out = %h (expected 01)", $time, cpu_data_out);

    // All done
    #50;
    $finish;
  end

  //--------------------------------------------------------------------------
  // dump signals
  //--------------------------------------------------------------------------
  initial begin
    $dumpfile("tb_l1_cache.vcd");
    $dumpvars(0, tb_l1_cache);
  end

endmodule

tb_l1_cache.vcd
$date
	Sun May  4 00:15:47 2025
$end
$version
	Icarus Verilog
$end
$timescale
	1ns
$end
$scope module tb_l1_cache $end
$var wire 1 ! l2_cache_write $end
$var wire 1 " l2_cache_ready $end
$var wire 1 # l2_cache_read $end
$var wire 1 $ l2_cache_hit $end
$var wire 128 % l2_cache_data_out [127:0] $end
$var wire 128 & l2_cache_data_in [127:0] $end
$var wire 11 ' l2_cache_addr [10:0] $end
$var wire 1 ( cpu_ready $end
$var wire 8 ) cpu_data_out [7:0] $end
$var parameter 32 * ADDR_WIDTH $end
$var parameter 32 + BLOCK_SIZE $end
$var parameter 32 , CACHE_SIZE $end
$var parameter 32 - DATA_WIDTH $end
$var parameter 32 . NUM_WAYS $end
$var reg 1 / clk $end
$var reg 11 0 cpu_addr [10:0] $end
$var reg 8 1 cpu_data_in [7:0] $end
$var reg 1 2 cpu_read $end
$var reg 1 3 cpu_write $end
$var reg 1 4 rst_n $end
$scope module dut $end
$var wire 1 / clk $end
$var wire 11 5 cpu_addr [10:0] $end
$var wire 8 6 cpu_data_in [7:0] $end
$var wire 1 2 cpu_read $end
$var wire 1 3 cpu_write $end
$var wire 1 7 l1_hit $end
$var wire 1 4 rst_n $end
$var wire 5 8 tag [4:0] $end
$var wire 1 " l2_cache_ready $end
$var wire 1 $ l2_cache_hit $end
$var wire 128 9 l2_cache_data_in [127:0] $end
$var wire 2 : index [1:0] $end
$var wire 4 ; byte_offset [3:0] $end
$var parameter 32 < ADDR_WIDTH $end
$var parameter 32 = BLOCK_SIZE $end
$var parameter 32 > BYTE_OFFSET_WIDTH $end
$var parameter 32 ? CACHE_SIZE $end
$var parameter 32 @ DATA_WIDTH $end
$var parameter 32 A INDEX_WIDTH $end
$var parameter 32 B NUM_BLOCKS $end
$var parameter 32 C NUM_SETS $end
$var parameter 32 D NUM_WAYS $end
$var parameter 34 E TAG_WIDTH $end
$var reg 8 F cpu_data_out [7:0] $end
$var reg 1 ( cpu_ready $end
$var reg 8 G data_found [7:0] $end
$var reg 1 H found $end
$var reg 1 I hit $end
$var reg 11 J l2_cache_addr [10:0] $end
$var reg 128 K l2_cache_data_out [127:0] $end
$var reg 1 # l2_cache_read $end
$var reg 1 ! l2_cache_write $end
$var reg 1 L reading_from_l2 $end
$var reg 1 M updated $end
$var integer 32 N i [31:0] $end
$scope begin $ivl_for_loop0 $end
$var integer 32 O j [31:0] $end
$upscope $end
$upscope $end
$scope module mem_inst $end
$var wire 11 P addr [10:0] $end
$var wire 1 / clk $end
$var wire 128 Q data_in [127:0] $end
$var wire 1 # read $end
$var wire 1 4 rst_n $end
$var wire 1 ! write $end
$var wire 11 R block_start [10:0] $end
$var parameter 32 S ADDR_WIDTH $end
$var parameter 32 T BLOCK_BITS $end
$var parameter 32 U BLOCK_SIZE $end
$var parameter 32 V DATA_WIDTH $end
$var parameter 43 W MEM_SIZE $end
$var reg 128 X data_out [127:0] $end
$var reg 1 $ hit $end
$var reg 1 " ready $end
$scope begin $ivl_for_loop1 $end
$var integer 32 Y i [31:0] $end
$upscope $end
$scope begin $ivl_for_loop2 $end
$var integer 32 Z i [31:0] $end
$upscope $end
$upscope $end
$scope task cpu_request $end
$var reg 11 [ addr [10:0] $end
$upscope $end
$upscope $end
$enddefinitions $end
$comment Show the parameter values. $end
$dumpall
b100000000000 W
b1000 V
b10000 U
b100 T
b1011 S
b101 E
b100 D
b100 C
b10000 B
b10 A
b1000 @
b100000000 ?
b100 >
b10000 =
b1011 <
b100 .
b1000 -
b100000000 ,
b10000 +
b1011 *
$end
#0
$dumpvars
bx [
bx Z
bx Y
bx X
bx0000 R
bx Q
bx P
bx O
b100 N
0M
xL
bx K
bx J
xI
0H
b0 G
bx F
b0 ;
b0 :
bx 9
b0 8
x7
b0 6
b0 5
04
03
02
b0 1
b0 0
0/
bx )
x(
bx '
bx &
bx %
x$
x#
x"
x!
$end
#5
1M
b0 R
0L
b0 %
b0 K
b0 Q
b0 '
b0 J
b0 P
0!
0#
1(
b0 &
b0 9
b0 X
0$
1"
b100000000000 Y
b100 O
b100 N
1/
#10
0/
#15
b100000000000 Y
b100 O
b100 N
1/
#20
b100 N
b1 ;
12
b1 0
b1 5
b1 [
0/
14
#25
1L
b1 '
b1 J
b1 P
1#
07
0I
0(
0"
1/
#30
0/
#35
1$
1"
b1111000011100000110100001100000010110000101000001001000010000000011100000110000001010000010000000011000000100000000100000000 &
b1111000011100000110100001100000010110000101000001001000010000000011100000110000001010000010000000011000000100000000100000000 9
b1111000011100000110100001100000010110000101000001001000010000000011100000110000001010000010000000011000000100000000100000000 X
b10000 Z
1/
#40
0/
#45
b0 ;
b0 0
b0 5
b0 [
0M
b0 G
1H
17
1I
b1 )
b1 F
1(
0L
b1111000011100000110100001100000010110000101000001001000010000000011100000110000001010000010000000011000000100000000100000000 %
b1111000011100000110100001100000010110000101000001001000010000000011100000110000001010000010000000011000000100000000100000000 K
b1111000011100000110100001100000010110000101000001001000010000000011100000110000001010000010000000011000000100000000100000000 Q
b0 '
b0 J
b0 P
0#
b10000 Z
b100 N
1/
#50
0/
#55
b0 )
b0 F
0$
0"
b10 G
b100 N
1H
b10 ;
b10 0
b10 5
b10 [
1/
#60
0/
#65
b10 )
b10 F
b100 N
b101 G
1H
b101 ;
b101 0
b101 5
b101 [
1/
#70
0/
#75
b101 )
b101 F
1M
b100 N
b0 G
0H
b1 :
b0 ;
b10000 0
b10000 5
b10000 [
1/
#80
0/
#85
b10000 R
1L
b10000 '
b10000 J
b10000 P
1#
07
0I
0(
1/
#90
0/
#95
1$
1"
b11111000111100001110100011100000110110001101000011001000110000001011100010110000101010001010000010011000100100001000100010000 &
b11111000111100001110100011100000110110001101000011001000110000001011100010110000101010001010000010011000100100001000100010000 9
b11111000111100001110100011100000110110001101000011001000110000001011100010110000101010001010000010011000100100001000100010000 X
b10000 Z
1/
#100
0/
#105
b100 ;
b10100 0
b10100 5
b10100 [
0M
b10100 G
1H
b0 R
17
1I
b10000 )
b10000 F
1(
0L
b11111000111100001110100011100000110110001101000011001000110000001011100010110000101010001010000010011000100100001000100010000 %
b11111000111100001110100011100000110110001101000011001000110000001011100010110000101010001010000010011000100100001000100010000 K
b11111000111100001110100011100000110110001101000011001000110000001011100010110000101010001010000010011000100100001000100010000 Q
b0 '
b0 J
b0 P
0#
b10000 Z
b100 N
1/
#110
0/
#115
b10100 )
b10100 F
0$
0"
b100 N
b11010 G
1H
b1010 ;
b11010 0
b11010 5
b11010 [
1/
#120
0/
#125
b11010 )
b11010 F
b100 N
b0 G
0H
b0 :
b1 ;
b100 8
b100000001 0
b100000001 5
b100000001 [
1/
#130
0/
#135
b100000000 R
1L
b100000001 '
b100000001 J
b100000001 P
1#
07
0I
0(
1/
#140
0/
#145
1$
1"
b1111000011100000110100001100000010110000101000001001000010000000011100000110000001010000010000000011000000100000000100000000 &
b1111000011100000110100001100000010110000101000001001000010000000011100000110000001010000010000000011000000100000000100000000 9
b1111000011100000110100001100000010110000101000001001000010000000011100000110000001010000010000000011000000100000000100000000 X
b10000 Z
1/
#150
0/
#155
b1 G
1H
b0 R
17
1I
b1 )
b1 F
1(
0L
b1111000011100000110100001100000010110000101000001001000010000000011100000110000001010000010000000011000000100000000100000000 %
b1111000011100000110100001100000010110000101000001001000010000000011100000110000001010000010000000011000000100000000100000000 K
b1111000011100000110100001100000010110000101000001001000010000000011100000110000001010000010000000011000000100000000100000000 Q
b0 '
b0 J
b0 P
0#
b10000 Z
b100 N
1/
#160
0/
#165
0$
0"
1/
